{
  "getAuthData": {
    "flag": "0",
    "desc": "获取认证信息:OK",
    "data": {
      "token": "f4be0f2745b348919b9fd5b8afbf8fd2",
      "expire": 7200,
      "userid": "40b6b763-31af-46b3-b4b3-c62296914c6d"
    }
  },
  "getTaskList": {
    "data": {
      "data": [
        {
          "billData": [
            {
              "name": "姓名",
              "value": "张三呀"
            },
            {
              "name": "流程",
              "value": "初审"
            }
          ],
          "taskId": "68fd48b4-ead6-11e7-9523-0242ac1e1105",
          "title": "张三的差旅费",
          "url": "USER_CUSTOMAPPROVE",
          "taskTime": 1587102875302,
          "committer": "提交人",
          "status": 1
        },
        {
          "billData": [
            {
              "name": "姓名",
              "value": "李四"
            },
            {
              "name": "流程",
              "value": "初审"
            }
          ],
          "taskId": "68fd48b4-ead6-11e7-9523-0242ac1e1106",
          "title": "李四的差旅费",
          "url": "USER_CUSTOMAPPROVE",
          "taskTime": 1587102875302,
          "committer": "提交人",
          "status": 1
        }
      ],
      "openType": "DIRECT",
      "moreUrl": "https://yonsuite.diwork.com/#/",
      "total": 1
    },
    "desc": "获取审批列表:OK",
    "flag": "0"
  },
  "getTaskCount": {
    "flag": "0",
    "data": 25,
    "desc": "获取待办数量:OK"
  },
  "getCCList": {
    "data": {
      "data": [{
        "billData": [
          {
            "name": "姓名",
            "value": "张三"
          },{
            "name": "流程",
            "value": "初审"
          }],
        "taskId":"68fd48b4-ead6-11e7-9523-0242ac1e1105",
        "title": "张三的差旅费",
        "url": "USER_CUSTOMAPPROVE",
        "taskTime": 1587102875302,
        "committer": "提交人",
        "status": 1
      }
      ],
      "openType": "DIRECT",
      "moreUrl": "https://yonsuite.diwork.com/#/",
      "total":1
    },
    "desc": "获取抄送列表:OK",
    "flag": "0"
  },
  "getSponsorList":{
    "data": {
      "data": [{
        "billData": [
          {
            "name": "姓名",
            "value": "王五"
          },{
            "name": "流程",
            "value": "初审"
          }],
        "taskId":"68fd48b4-ead6-11e7-9523-0242ac1e1107",
        "title": "王五的差旅费",
        "url": "USER_CUSTOMAPPROVE",
        "taskTime": 1587102875302,
        "committer": "提交人",
        "status": 1
      }
      ],
      "openType": "DIRECT",
      "moreUrl": "https://yonsuite.diwork.com/#/",
      "total":1
    },
    "desc": "获取我的发起列表:OK",
    "flag": "0"
  },
  "doAction": {
    "data": [{
      "taskId":"68fd48b4-ead6-11e7-9523-0242ac1e1105",
      "status":true,
      "errmsg":"",
      "multi":true
    },
      {
        "taskId":"68fd48b4-ead6-11e7-9523-0242ac1e1106",
        "status":true ,
        "errmsg":"",
        "multi":true
      }],
    "desc": "直接审批，批量审批接口:OK",
    "flag": "0"
  },
  "getFilters": {
    "code": "",
    "data": [
      {
        "filterId": "receiveDate",
        "name": "接收时间",
        "combo": 0,
        "type": "date",
        "status": "1,2,3",
        "params": [
          {
            "name": "今天",
            "value": "today"
          },
          {
            "name": "昨天",
            "value": "yesterday"
          },
          {
            "name": "本周",
            "value": "thisWeek"
          },
          {
            "name": "上周",
            "value": "lastWeek"
          },
          {
            "name": "本月",
            "value": "month"
          },
          {
            "name": "自定义",
            "value": "custom"
          }
        ]
      },
      {
        "filterId": "processKey",
        "name": "单据类型",
        "combo": 0,
        "type": "choice",
        "status": "1,2,3",
        "params": [
          {
            "name": "请假单",
            "value": "QJD"
          },
          {
            "name": "补考勤",
            "value": "BKQ"
          },
          {
            "name": "报销单",
            "value": "BXD"
          }
        ]
      }
    ],
    "desc": "获取过滤器列表:OK",
    "flag": "0"
  },
  "pageMeta": {
    "flag":"0",
    "desc":"获取界面定义元数据:OK",
    "data":{
      "tab":[
        {
          "urlType":"inner",
          "showName":"详情",
          "tabCode":"pageDetail"
        },
        {
          "urlType":"inner",
          "showName":"流程历史",
          "tabCode":"flowHis"
        },
        {
          "urlType":"inner",
          "showName":"附件",
          "tabCode":"annexList"
        }
      ],
      "services":[
        {
          "code":"pageDetail",
          "resp":[
            "pageDetail"
          ],
          "delay":false
        },
        {
          "code":"flowHis",
          "resp":[
            "flowHis"
          ],
          "delay":false
        },
        {
          "code":"annexList",
          "resp":[
            "annexList"
          ],
          "delay":false
        },
        {
          "code":"pageTitle",
          "resp":[
            "pageTitle"
          ],
          "delay":false
        },
        {
          "code":"pageStatus",
          "resp":[
            "pageStatus"
          ],
          "delay":false
        },
        {
          "code":"annexNum",
          "resp":[
            "annexNum"
          ],
          "delay":false
        },
        {
          "code":"actionList",
          "resp":[
            "actionList"
          ],
          "delay":false
        },
        {
          "code":"actionDetail",
          "resp":[
            "actionDetail"
          ],
          "delay":false
        }
      ]
    }
  },
  "pageTitle": {
    "flag":"0",
    "desc":"获取标题：OK",
    "code":"0",
    "data":{
      "pageTitle":{
        "data":"康旺的上线申请",
        "flag":"0",
        "desc":"sueecss",
        "showError":true
      }
    }
  },
  "pageStatus": {
    "flag":"0",
    "desc":"OK",
    "data":{
      "pageStatus":{
        "data":{
          "text":"审批中",
          "status":"going"
        },
        "flag":"0",
        "desc":"OK",
        "showError":true
      }
    }
  },
  "pageUrls": {
    "flag": "0",
    "desc": "头部跳转地址:OK",
    "data": {
      "pageUrls": {
        "data": [
          {
            "urlType": "inner",
            "showName": "单据全貌",
            "tabCode": "pageContent"
          },
          {
            "urlType": "inner",
            "showName": "流程图",
            "tabCode": "flowHisIcon"
          },
          {
            "urlType": "url",
            "showName": "baidu",
            "url": "https://baidu.com"
          }],
        "flag": "0",
        "desc": "sueecss",
        "showError": false
      }
    }
  },
  "pageDetail": {
    "flag":"0",
    "desc":"页面详情:OK",
    "data":{
      "pageDetail":{
        "data":{
          "h":[
            {
              "tabName":"上线申请",
              "tabContent":{
                "itemData":[
                  {
                    "itemValue":"上线申请",
                    "itemName":"单据类型"
                  },
                  {
                    "itemValue":"0204",
                    "itemName":"自动编号"
                  },
                  {
                    "itemValue":"康旺",
                    "itemName":"用户"
                  },
                  {
                    "itemValue":"云平台技术中台产品部",
                    "itemName":"申请人部门"
                  },
                  {
                    "itemValue":"用友网络科技股份有限公司",
                    "itemName":"申请人所在组织"
                  }
                ]
              }
            }
          ],
          "b":[
            {
              "tabName":"故事清单",
              "tabNum":3,
              "tabContent":[
                {
                  "itemData":[
                    {
                      "itemName":"故事1",
                      "itemValue":"在镜像仓库中，增加用户镜像的隔离功能",
                      "igest":false
                    }
                  ]
                },
                {
                  "itemData":[
                    {
                      "itemName":"故事2",
                      "itemValue":"在灰度发布功能中，增加全局公共规则配置",
                      "igest":false
                    }
                  ]
                },
                {
                  "itemData":[
                    {
                      "itemName":"故事3",
                      "itemValue":"流水线接入JIRA系统，流水线各环境代码发布后更改对应JIRA状态",
                      "igest":false
                    }
                  ]
                }
              ]
            }
          ],
          "billtypename":"审批详情"
        },
        "flag":"0",
        "desc":"OK",
        "showError":true
      }
    },
    "sysType":"GENERAL"
  },
  "pageContent": {
    "flag":"0",
    "desc":"单据正文:OK",
    "data":{
      "pageContent":{
        "data":{
          "html":"https://www.json.cn/"
        },
        "flag":"0",
        "desc":"sueecss",
        "showError":false
      }
    }
  },
  "flowHis": {
    "flag":"0",
    "desc":"OK",
    "data":{
      "flowHis":{
        "data":[
          {
            "note":"应用1上线申请",
            "dealTime":"2020-3-12",
            "action":"提交",
            "userName":"康旺",
            "type":"commit",
            "userId":"XXXXXXXXXX",
            "taskId":"68fd48b4-ead6-11e7-9523-0242ac1e1105",
            "status":"1"
          },
          {
            "note":"没问题",
            "dealTime":"2020-3-13",
            "action":"同意",
            "userName":"王伟",
            "type":"going",
            "userId":"XXXXXXXXXX",
            "taskId":"68fd48b4-ead6-11e7-9523-0242ac1e1105",
            "status":"1"
          },
          {
            "note":"可以上线",
            "dealTime":"2020-3-14",
            "action":"同意",
            "userName":"李先",
            "type":"going",
            "userId":"XXXXXXXXXX",
            "taskId":"68fd48b4-ead6-11e7-9523-0242ac1e1105",
            "status":"1"
          }
        ],
        "flag":"0",
        "desc":"OK",
        "showError":true
      }
    }
  },
  "flowHisIcon": {
    "flag":"0",
    "desc":"流程图:OK",
    "data":{
      "flowHisIcon":{
        "data":{
          "icon":"https://cdn.yonyoucloud.com/pro/diwork/appicon/Artboard+2+Copy+12.png",
          "subIcon":"https://cdn.yonyoucloud.com/pro/diwork/appicon/Artboard+2+Copy+22.png"
        },
        "flag":"0",
        "desc":"sueecss",
        "showError":false
      }
    }
  },
  "annexNum": {
    "flag":"0",
    "desc":"OK",
    "data":{
      "annexNum":{
        "data":{
          "number":1
        },
        "flag":"0",
        "desc":"OK",
        "showError":true
      }
    }
  },
  "annexList": {
    "flag":"0",
    "desc":"OK",
    "data":{
      "annexList":{
        "data":[
          {
            "filetype":"xls",
            "filename":"故事清单.xls",
            "previewUrl":"https//developer.yonyoucloud.com",
            "downflag":"1",
            "downloadUrl":"https//developer.yonyoucloud.com",
            "filesize":"30KB",
            "dnType":"2",
            "fileid":"38e6b5a2-4c13-4cda-85fa-c38aa7384fc3"
          }
        ],
        "flag":"0",
        "desc":"OK",
        "showError":true
      }
    }
  },
  "actionList": {
    "flag":"0",
    "desc":"审批动作列表:OK",
    "data":{
      "actionList":{
        "data":[
          {
            "actionCode":"doAgree",
            "actionName":"批准",
            "order":0
          },
          {
            "actionCode":"doDisAgree",
            "actionName":"不批准",
            "order":1
          },
          {
            "actionCode":"doReject",
            "actionName":"驳回",
            "order":2
          },
          {
            "actionCode":"doReassign",
            "actionName":"改派",
            "order":3
          },
          {
            "actionCode":"doAddApprove",
            "actionName":"加签",
            "order":4
          }],
        "flag":"0",
        "desc":"sueecss",
        "showError":false
      }
    }
  },
  "actionDetail": {
    "flag": "0",
    "desc": "获取审批动作详情:OK",
    "data": {
      "actionDetail": {
        "data": {
          "detail":[
            {
              "paramType": "main",
              "paramKey": "agree",
              "paramPlace": "默认值",
              "showPhBook": 0,
              "savePhBook": 0,
              "order": 0,
              "required":true
            },
            {
              "paramType": "handSign",
              "paramKey": "agree",
              "order": 1
            },
            {
              "paramType": "text",
              "paramKey": "agree",
              "paramPlace": "默认值",
              "paramName": "文本输入",
              "order": 2
            },
            {
              "paramType": "radio",
              "paramKey": "agree",
              "isMult": 0,
              "paramName": "指派人",
              "order": 3,
              "redio": [
                {
                  "key": "Y",
                  "value": "是"
                }]
            },
            {
              "paramType": "ref",
              "paramKey": "agree123",
              "paramName": "指派人",
              "isMult": 0,
              "ref": {
                "action": "geteeee",
                "showSearch": 0
              },
              "subRef": {
                "isMult": 0,
                "action": "geteeee",
                "showSearch": 0
              },
              "order": 4
            }
          ],
          "type":0
        }
      }
    }
  }
}